{
  "main": {
    "id": "7130117a15207410",
    "type": "split",
    "children": [
      {
        "id": "fb23e5b52c875d28",
        "type": "tabs",
        "children": [
          {
            "id": "48231ec2fb858e67",
            "type": "leaf",
            "state": {
              "type": "markdown",
              "state": {
                "file": "项目 project/BOT 防护/工作量证明 Pow.md",
                "mode": "preview",
                "backlinks": false,
                "source": false
              }
            }
          }
        ]
      }
    ],
    "direction": "vertical"
  },
  "left": {
    "id": "0a280ff3a1982f9c",
    "type": "split",
    "children": [
      {
        "id": "4c6164bdbc48c666",
        "type": "tabs",
        "children": [
          {
            "id": "f20c19f843ae697d",
            "type": "leaf",
            "state": {
              "type": "file-explorer",
              "state": {
                "sortOrder": "alphabetical"
              }
            }
          },
          {
            "id": "435137fc76d35983",
            "type": "leaf",
            "state": {
              "type": "search",
              "state": {
                "query": "",
                "matchingCase": false,
                "explainSearch": false,
                "collapseAll": false,
                "extraContext": false,
                "sortOrder": "alphabetical"
              }
            }
          },
          {
            "id": "1696bda18e687e09",
            "type": "leaf",
            "state": {
              "type": "bookmarks",
              "state": {}
            }
          }
        ]
      }
    ],
    "direction": "horizontal",
    "width": 354.5
  },
  "right": {
    "id": "b5bfeafd50690429",
    "type": "split",
    "children": [
      {
        "id": "c9b081027618650f",
        "type": "tabs",
        "children": [
          {
            "id": "b787158987e7965f",
            "type": "leaf",
            "state": {
              "type": "backlink",
              "state": {
                "file": "项目 project/BOT 防护/工作量证明 Pow.md",
                "collapseAll": false,
                "extraContext": false,
                "sortOrder": "alphabetical",
                "showSearch": false,
                "searchQuery": "",
                "backlinkCollapsed": false,
                "unlinkedCollapsed": true
              }
            }
          },
          {
            "id": "0e59c140f263b4b5",
            "type": "leaf",
            "state": {
              "type": "outgoing-link",
              "state": {
                "file": "项目 project/BOT 防护/工作量证明 Pow.md",
                "linksCollapsed": false,
                "unlinkedCollapsed": true
              }
            }
          },
          {
            "id": "ac9287d275a45b46",
            "type": "leaf",
            "state": {
              "type": "tag",
              "state": {
                "sortOrder": "frequency",
                "useHierarchy": true
              }
            }
          },
          {
            "id": "287905a7625d372e",
            "type": "leaf",
            "state": {
              "type": "all-properties",
              "state": {
                "sortOrder": "frequency"
              }
            }
          },
          {
            "id": "a6963b314ce0bb03",
            "type": "leaf",
            "state": {
              "type": "outline",
              "state": {
                "file": "项目 project/BOT 防护/工作量证明 Pow.md"
              }
            }
          }
        ]
      }
    ],
    "direction": "horizontal",
    "width": 300
  },
  "left-ribbon": {
    "hiddenItems": {
      "graph:查看关系图谱": false,
      "canvas:新建白板": false,
      "daily-notes:打开/创建今天的日记": false,
      "templates:插入模板": false,
      "markdown-importer:打开 Markdown 格式转换器": false,
      "switcher:打开快速切换": false,
      "command-palette:打开命令面板": false
    }
  },
  "active": "48231ec2fb858e67",
  "lastOpenFiles": [
    "项目 project/流式检测.md",
    "Git 知识库/code review 规范.md",
    "未命名.canvas",
    "八股文 eight-part essay writing/NodeJS/koa.md",
    "八股文 eight-part essay writing/assets/boce40/1647342652227-761c4858-30be-43b2-93a0-3cf0f0f81648.png",
    "八股文 eight-part essay writing/assets/ae6e6m/1651743183816-ed2571e8-fd14-450e-a48f-a2574f26c4e5.png",
    "Git 知识库/常用 git 命令.md",
    "Git 知识库/commit message 代码提交信息规范.md",
    "项目 project/assets/axtgz0utigbgne3g/1699508023913-09180d5d-288a-46c5-bfa3-69ffff7eec2d.png",
    "项目 project/BOT 防护/浏览器指纹验证.md",
    "项目 project/BOT 防护/工作量证明 Pow.md",
    "项目 project/assets/axtgz0utigbgne3g",
    "项目 project/性能优化",
    "项目 project/BOT 防护",
    "项目 project/assets",
    "项目 project/RBAC",
    "项目 project/GeoJSON 和 TopoJSON 转换",
    "项目 project",
    "项目 Project/流式检测.md",
    "项目梳理/项目/滴滴出行小程序/行程中.md",
    "项目梳理/项目/滴滴出行小程序/小程序包体积优化.md",
    "项目梳理/项目/滴滴出行小程序/冒泡页.md",
    "项目梳理/项目/滴滴出行小程序/mpx 性能优化.md",
    "项目梳理/项目/小程序上线管理平台/数据库表设计.md",
    "项目梳理/项目/小程序上线管理平台/发布方式.md",
    "项目梳理/项目/小程序上线管理平台/原型设计.md",
    "项目梳理/项目/小程序上线管理平台/介绍.md",
    "项目梳理/assets/qf3q0x/1650901762867-6477f823-8c3d-4eef-9502-d48b6a7e1d86.png",
    "项目梳理/assets/qf3q0x/1650900285959-8bdd0433-9c77-41d7-97dd-0ea90b5741ff.png",
    "项目梳理/assets/mo05y7/1650004194883-141c271f-7e8b-4e50-922b-e120597edf9f.png",
    "项目梳理/assets/hgoyws/1650700691862-fe9f8984-cc57-46f6-9959-74c1599c4474.png",
    "项目梳理/assets/hgoyws/1650700504522-96376a3d-276b-4f10-b14d-db86f456c71b.png",
    "项目梳理/assets/hgoyws/1650699968107-bfe9dc4d-2cdf-4e5b-93a1-c773a1d2766e.png",
    "项目梳理/assets/flzwri/1657000497150-644f2744-2ea7-4fa0-8755-16394cc5c9d7.png",
    "项目梳理/项目/长列表性能优化.md",
    "项目梳理/项目/滴滴出行小程序",
    "项目梳理/项目/小程序体验分优化.md",
    "项目梳理/项目/小程序上线管理平台",
    "项目梳理/项目/利用 ts + proxy 增强 api 类型推导功能.md",
    "项目梳理/项目/人工审核系统.md",
    "项目梳理/项目/webx.md",
    "项目梳理/项目/mpx.md",
    "项目梳理/项目/TypeScript 在团队内部的实践总结.md",
    "项目梳理/小程序接入原子化 css 样式库并支持分包输出/架构设计.md",
    "项目梳理/小程序接入原子化 css 样式库并支持分包输出/备忘录.md",
    "项目梳理/assets/qf3q0x"
  ]
}