{
  "id": 77021632,
  "slug": "vd2h4l",
  "title": "Promise  常用方法实现",
  "description": "Promise.allPromise.all 方法用于将多个 Promise 实例，包装成一个新的 Promise 实例。如果每个实例都成功，会将所有实例的返回值组成一个数组如果其中一个实例运行失败，则返回最先失败的实例结果（在创建实例的时候，promise.all 内部的实例就已经执行了，无...",
  "cover": "",
  "user_id": 732231,
  "book_id": 27818302,
  "last_editor_id": 732231,
  "format": "lake",
  "body_draft": "",
  "body": "<a name=\"OgAA4\"></a>\n## Promise.all\n`Promise.all` 方法用于将多个 `Promise` 实例，包装成一个新的 `Promise` 实例。\n\n- 如果每个实例都成功，会将所有实例的返回值组成一个数组\n- 如果其中一个实例运行失败，则返回最先失败的实例结果（在创建实例的时候，`promise.all` 内部的实例就已经执行了，无论哪一个失败）\n```javascript\nPromise.prototype.all = promises => {\n\treturn new Promise((resolve, reject) => {\n  \t// 计数器\n    let count = 0\n    // 存放结果\n    let result = []\n    let len = promises.length\n    if (len === 0) return resolve([])\n    promises.forEach((item, index) => {\n    \t// 注意有的数组项有可能不是 Promise，需要手动转化一下\n      Promise.resolve(item).then(res => {\n      \tcount += 1\n        // 收集每个 Promise 的返回值\n       \tresult[i] = res\n        // 当所有的 Promise 都成功了，那么将返回 Promise 结果\n        if(count === len) {\n        \tresolve(result)\n        }\n      }).catch(err => reject(err))\n    })\n  })\n}\n```\n<a name=\"N2V7r\"></a>\n## Promise.allSettled\n有时候，我们希望等到一组异步操作都结束了，不管一个操作是成功还是失败，再进行下一步操作。而 `Promise.all` (其只要是一个失败了，结果即进入失败状态)不太合适，所以有了 `Promise.allSettled`\n\n只有等到参数数组的所有 `Promise` 对象都发生状态变更(不管是 `fulfilled` 还是 `rejected`)，返回的 `Promise` 对象才会发生状态变更，一旦发生状态变更，状态总是 `fulfilled`，不会变成 `rejected`\n```javascript\nPromise.prototype.allSettled = promises => {\n\treturn new Promise((resolve, reject) => {\n  \tlet count = 0\n    let result = []\n    let len = promises.length\n    // 数组是空的话，直接返回空数组\n    if (len === 0) return resolve([])\n    promises.forEach((item, index) => {\n    \tPromise.resolve(item).then(res => {\n      \tcount += 1\n        // 成功属性设置\n        result[i] = {\n        \tstatus: 'fulfilled',\n          value: res\n        }\n        if (count === len) {\n        \tresolve(result)\n        }\n      }).catch(err => {\n      \tcount += 1\n        // 失败属性设置\n        result[i] = {\n        \tstatus: 'rejected',\n          reason: err\n        }\n        if (count === len) {\n        \tresolve(result)\n        }\n      })\n    })\n  })\n}\n```\n<a name=\"m5Trz\"></a>\n## Promise.race\n传入的所有实例哪一个实例的状态率先改变，那么就会返回哪个实例的返回值。无论成功还是失败\n```javascript\nPromise.prototype.race = promises => {\n\treturn new Promise((resolve, reject) => {\n  \tpromises.forEach(item => {\n  \t\t// 此处需要做二次包装，防止非 Promise 对象\n      // 同时进行状态监听\n      Promise.resolve(item)\n        .then(value => resolve(value))\n        .catch(err => reject(err))\n  \t})\n  })\n}\n```\n<a name=\"jdISu\"></a>\n## Promise.any\n只有全部实例都失败后才会返回失败，如果有一个实例的状态返回成功，则返回第一个成功的实例\n```javascript\nPromise.prototype.any = promises => {\n  return new Promise((resolve, reject) => {\n    let count = 0\n  \tlet len = promiseList.length\n    if (len === 0) return\n    promises.forEach(item => {\n    \tPromise.resolve(item)\n      \t.then(value => resolve(value))\n      \t.catch(err => {\n      \t\tcount+=1\n        \tif (count === len) {\n          \treturn reject(new Error('All promises where rejected'))\n          }\n      \t})\n    })\n  })\n}\n```\n",
  "body_html": "<!doctype html><h2 id=\"OgAA4\"><span>Promise.all</span></h2><p data-lake-id=\"ua757dd8b\"><code><span>Promise.all</span></code><span> 方法用于将多个 </span><code><span>Promise</span></code><span> 实例，包装成一个新的 </span><code><span>Promise</span></code><span> 实例。</span></p><ul><li><span>如果每个实例都成功，会将所有实例的返回值组成一个数组</span></li><li><span>如果其中一个实例运行失败，则返回最先失败的实例结果（在创建实例的时候，</span><code><span>promise.all</span></code><span> 内部的实例就已经执行了，无论哪一个失败）</span></li></ul><pre data-lang=\"javascript\"><code>Promise.prototype.all = promises =&gt; {\n\treturn new Promise((resolve, reject) =&gt; {\n  \t// 计数器\n    let count = 0\n    // 存放结果\n    let result = []\n    let len = promises.length\n    if (len === 0) return resolve([])\n    promises.forEach((item, index) =&gt; {\n    \t// 注意有的数组项有可能不是 Promise，需要手动转化一下\n      Promise.resolve(item).then(res =&gt; {\n      \tcount += 1\n        // 收集每个 Promise 的返回值\n       \tresult[i] = res\n        // 当所有的 Promise 都成功了，那么将返回 Promise 结果\n        if(count === len) {\n        \tresolve(result)\n        }\n      }).catch(err =&gt; reject(err))\n    })\n  })\n}</code></pre><h2 id=\"N2V7r\"><span>Promise.allSettled</span></h2><p data-lake-id=\"u10bb6481\"><span>有时候，我们希望等到一组异步操作都结束了，不管一个操作是成功还是失败，再进行下一步操作。而 </span><code><span>Promise.all</span></code><span> (其只要是一个失败了，结果即进入失败状态)不太合适，所以有了 </span><code><span>Promise.allSettled</span></code></p><p data-lake-id=\"u83a79e11\"><br /></p><p data-lake-id=\"u210f5b9b\"><span>只有等到参数数组的所有 </span><code><span>Promise</span></code><span> 对象都发生状态变更(不管是 </span><code><span>fulfilled</span></code><span> 还是 </span><code><span>rejected</span></code><span>)，返回的 </span><code><span>Promise</span></code><span> 对象才会发生状态变更，一旦发生状态变更，状态总是 </span><code><span>fulfilled</span></code><span>，不会变成 </span><code><span>rejected</span></code></p><pre data-lang=\"javascript\"><code>Promise.prototype.allSettled = promises =&gt; {\n\treturn new Promise((resolve, reject) =&gt; {\n  \tlet count = 0\n    let result = []\n    let len = promises.length\n    // 数组是空的话，直接返回空数组\n    if (len === 0) return resolve([])\n    promises.forEach((item, index) =&gt; {\n    \tPromise.resolve(item).then(res =&gt; {\n      \tcount += 1\n        // 成功属性设置\n        result[i] = {\n        \tstatus: 'fulfilled',\n          value: res\n        }\n        if (count === len) {\n        \tresolve(result)\n        }\n      }).catch(err =&gt; {\n      \tcount += 1\n        // 失败属性设置\n        result[i] = {\n        \tstatus: 'rejected',\n          reason: err\n        }\n        if (count === len) {\n        \tresolve(result)\n        }\n      })\n    })\n  })\n}</code></pre><h2 id=\"m5Trz\"><span>Promise.race</span></h2><p data-lake-id=\"u9d03eb9f\"><span>传入的所有实例哪一个实例的状态率先改变，那么就会返回哪个实例的返回值。无论成功还是失败</span></p><pre data-lang=\"javascript\"><code>Promise.prototype.race = promises =&gt; {\n\treturn new Promise((resolve, reject) =&gt; {\n  \tpromises.forEach(item =&gt; {\n  \t\t// 此处需要做二次包装，防止非 Promise 对象\n      // 同时进行状态监听\n      Promise.resolve(item)\n        .then(value =&gt; resolve(value))\n        .catch(err =&gt; reject(err))\n  \t})\n  })\n}</code></pre><h2 id=\"jdISu\"><span>Promise.any</span></h2><p data-lake-id=\"u44584718\"><span>只有全部实例都失败后才会返回失败，如果有一个实例的状态返回成功，则返回第一个成功的实例</span></p><pre data-lang=\"javascript\"><code>Promise.prototype.any = promises =&gt; {\n  return new Promise((resolve, reject) =&gt; {\n    let count = 0\n  \tlet len = promiseList.length\n    if (len === 0) return\n    promises.forEach(item =&gt; {\n    \tPromise.resolve(item)\n      \t.then(value =&gt; resolve(value))\n      \t.catch(err =&gt; {\n      \t\tcount+=1\n        \tif (count === len) {\n          \treturn reject(new Error('All promises where rejected'))\n          }\n      \t})\n    })\n  })\n}</code></pre>",
  "body_lake": "<!doctype lake><meta name=\"doc-version\" content=\"1\" /><meta name=\"typography\" content=\"classic\" /><meta name=\"viewport\" content=\"adapt\" /><h2 data-lake-id=\"OgAA4\" id=\"OgAA4\"><span data-lake-id=\"uf8ba0563\" id=\"uf8ba0563\">Promise.all</span></h2><p data-lake-id=\"ua757dd8b\" id=\"ua757dd8b\"><code data-lake-id=\"u83e7a166\" id=\"u83e7a166\"><span data-lake-id=\"u3a47b8b4\" id=\"u3a47b8b4\">Promise.all</span></code><span data-lake-id=\"u4baf1c4b\" id=\"u4baf1c4b\"> 方法用于将多个 </span><code data-lake-id=\"u051b9f0c\" id=\"u051b9f0c\"><span data-lake-id=\"u5e4f38c7\" id=\"u5e4f38c7\">Promise</span></code><span data-lake-id=\"ub256277b\" id=\"ub256277b\"> 实例，包装成一个新的 </span><code data-lake-id=\"u96026a5a\" id=\"u96026a5a\"><span data-lake-id=\"u8e580469\" id=\"u8e580469\">Promise</span></code><span data-lake-id=\"u3ba0b801\" id=\"u3ba0b801\"> 实例。</span></p><ul list=\"ubb325e60\"><li fid=\"u2b46873c\" data-lake-id=\"uab7c154b\" id=\"uab7c154b\"><span data-lake-id=\"uac080284\" id=\"uac080284\">如果每个实例都成功，会将所有实例的返回值组成一个数组</span></li><li fid=\"u2b46873c\" data-lake-id=\"u1f6abcfb\" id=\"u1f6abcfb\"><span data-lake-id=\"ubd2c5b38\" id=\"ubd2c5b38\">如果其中一个实例运行失败，则返回最先失败的实例结果（在创建实例的时候，</span><code data-lake-id=\"ued21d4a1\" id=\"ued21d4a1\"><span data-lake-id=\"ue85a58c3\" id=\"ue85a58c3\">promise.all</span></code><span data-lake-id=\"ub4c5bd02\" id=\"ub4c5bd02\"> 内部的实例就已经执行了，无论哪一个失败）</span></li></ul><card type=\"inline\" name=\"codeblock\" value=\"data:%7B%22mode%22%3A%22javascript%22%2C%22code%22%3A%22Promise.prototype.all%20%3D%20promises%20%3D%3E%20%7B%5Cn%5Ctreturn%20new%20Promise((resolve%2C%20reject)%20%3D%3E%20%7B%5Cn%20%20%5Ct%2F%2F%20%E8%AE%A1%E6%95%B0%E5%99%A8%5Cn%20%20%20%20let%20count%20%3D%200%5Cn%20%20%20%20%2F%2F%20%E5%AD%98%E6%94%BE%E7%BB%93%E6%9E%9C%5Cn%20%20%20%20let%20result%20%3D%20%5B%5D%5Cn%20%20%20%20let%20len%20%3D%20promises.length%5Cn%20%20%20%20if%20(len%20%3D%3D%3D%200)%20return%20resolve(%5B%5D)%5Cn%20%20%20%20promises.forEach((item%2C%20index)%20%3D%3E%20%7B%5Cn%20%20%20%20%5Ct%2F%2F%20%E6%B3%A8%E6%84%8F%E6%9C%89%E7%9A%84%E6%95%B0%E7%BB%84%E9%A1%B9%E6%9C%89%E5%8F%AF%E8%83%BD%E4%B8%8D%E6%98%AF%20Promise%EF%BC%8C%E9%9C%80%E8%A6%81%E6%89%8B%E5%8A%A8%E8%BD%AC%E5%8C%96%E4%B8%80%E4%B8%8B%5Cn%20%20%20%20%20%20Promise.resolve(item).then(res%20%3D%3E%20%7B%5Cn%20%20%20%20%20%20%5Ctcount%20%2B%3D%201%5Cn%20%20%20%20%20%20%20%20%2F%2F%20%E6%94%B6%E9%9B%86%E6%AF%8F%E4%B8%AA%20Promise%20%E7%9A%84%E8%BF%94%E5%9B%9E%E5%80%BC%5Cn%20%20%20%20%20%20%20%5Ctresult%5Bi%5D%20%3D%20res%5Cn%20%20%20%20%20%20%20%20%2F%2F%20%E5%BD%93%E6%89%80%E6%9C%89%E7%9A%84%20Promise%20%E9%83%BD%E6%88%90%E5%8A%9F%E4%BA%86%EF%BC%8C%E9%82%A3%E4%B9%88%E5%B0%86%E8%BF%94%E5%9B%9E%20Promise%20%E7%BB%93%E6%9E%9C%5Cn%20%20%20%20%20%20%20%20if(count%20%3D%3D%3D%20len)%20%7B%5Cn%20%20%20%20%20%20%20%20%5Ctresolve(result)%5Cn%20%20%20%20%20%20%20%20%7D%5Cn%20%20%20%20%20%20%7D).catch(err%20%3D%3E%20reject(err))%5Cn%20%20%20%20%7D)%5Cn%20%20%7D)%5Cn%7D%22%2C%22autoWrap%22%3Afalse%2C%22heightLimit%22%3Atrue%2C%22collapsed%22%3Afalse%2C%22name%22%3A%22%22%2C%22tabSize%22%3Anull%2C%22indentWithTab%22%3Afalse%2C%22lightLines%22%3A%5B%5D%2C%22foldLines%22%3A%5B%5D%2C%22theme%22%3A%22One%20Dark%20Pro%22%2C%22__spacing%22%3A%22both%22%2C%22id%22%3A%22AZX8h%22%2C%22margin%22%3A%7B%22top%22%3Atrue%2C%22bottom%22%3Atrue%7D%7D\"></card><h2 data-lake-id=\"N2V7r\" id=\"N2V7r\"><span data-lake-id=\"u58b20d23\" id=\"u58b20d23\">Promise.allSettled</span></h2><p data-lake-id=\"u10bb6481\" id=\"u10bb6481\"><span data-lake-id=\"u7bd9468c\" id=\"u7bd9468c\">有时候，我们希望等到一组异步操作都结束了，不管一个操作是成功还是失败，再进行下一步操作。而 </span><code data-lake-id=\"u288ab639\" id=\"u288ab639\"><span data-lake-id=\"uee093dce\" id=\"uee093dce\">Promise.all</span></code><span data-lake-id=\"u1bc21632\" id=\"u1bc21632\"> (其只要是一个失败了，结果即进入失败状态)不太合适，所以有了 </span><code data-lake-id=\"u7a28b616\" id=\"u7a28b616\"><span data-lake-id=\"u2e0fefe8\" id=\"u2e0fefe8\">Promise.allSettled</span></code></p><p data-lake-id=\"u83a79e11\" id=\"u83a79e11\"><br></p><p data-lake-id=\"u210f5b9b\" id=\"u210f5b9b\"><span data-lake-id=\"u2b380f96\" id=\"u2b380f96\">只有等到参数数组的所有 </span><code data-lake-id=\"uec601b9a\" id=\"uec601b9a\"><span data-lake-id=\"u6bc67070\" id=\"u6bc67070\">Promise</span></code><span data-lake-id=\"u79f123e9\" id=\"u79f123e9\"> 对象都发生状态变更(不管是 </span><code data-lake-id=\"u24c61bdc\" id=\"u24c61bdc\"><span data-lake-id=\"uc660ca34\" id=\"uc660ca34\">fulfilled</span></code><span data-lake-id=\"uc2f93828\" id=\"uc2f93828\"> 还是 </span><code data-lake-id=\"u659f443e\" id=\"u659f443e\"><span data-lake-id=\"u9e14a9de\" id=\"u9e14a9de\">rejected</span></code><span data-lake-id=\"uc1793761\" id=\"uc1793761\">)，返回的 </span><code data-lake-id=\"u7054fe1a\" id=\"u7054fe1a\"><span data-lake-id=\"u130b0651\" id=\"u130b0651\">Promise</span></code><span data-lake-id=\"uf7c1b972\" id=\"uf7c1b972\"> 对象才会发生状态变更，一旦发生状态变更，状态总是 </span><code data-lake-id=\"ueb2de0bf\" id=\"ueb2de0bf\"><span data-lake-id=\"u6f3bc033\" id=\"u6f3bc033\">fulfilled</span></code><span data-lake-id=\"u2dbce7af\" id=\"u2dbce7af\">，不会变成 </span><code data-lake-id=\"ucb2882dc\" id=\"ucb2882dc\"><span data-lake-id=\"u2ae17809\" id=\"u2ae17809\">rejected</span></code></p><card type=\"inline\" name=\"codeblock\" value=\"data:%7B%22mode%22%3A%22javascript%22%2C%22code%22%3A%22Promise.prototype.allSettled%20%3D%20promises%20%3D%3E%20%7B%5Cn%5Ctreturn%20new%20Promise((resolve%2C%20reject)%20%3D%3E%20%7B%5Cn%20%20%5Ctlet%20count%20%3D%200%5Cn%20%20%20%20let%20result%20%3D%20%5B%5D%5Cn%20%20%20%20let%20len%20%3D%20promises.length%5Cn%20%20%20%20%2F%2F%20%E6%95%B0%E7%BB%84%E6%98%AF%E7%A9%BA%E7%9A%84%E8%AF%9D%EF%BC%8C%E7%9B%B4%E6%8E%A5%E8%BF%94%E5%9B%9E%E7%A9%BA%E6%95%B0%E7%BB%84%5Cn%20%20%20%20if%20(len%20%3D%3D%3D%200)%20return%20resolve(%5B%5D)%5Cn%20%20%20%20promises.forEach((item%2C%20index)%20%3D%3E%20%7B%5Cn%20%20%20%20%5CtPromise.resolve(item).then(res%20%3D%3E%20%7B%5Cn%20%20%20%20%20%20%5Ctcount%20%2B%3D%201%5Cn%20%20%20%20%20%20%20%20%2F%2F%20%E6%88%90%E5%8A%9F%E5%B1%9E%E6%80%A7%E8%AE%BE%E7%BD%AE%5Cn%20%20%20%20%20%20%20%20result%5Bi%5D%20%3D%20%7B%5Cn%20%20%20%20%20%20%20%20%5Ctstatus%3A%20'fulfilled'%2C%5Cn%20%20%20%20%20%20%20%20%20%20value%3A%20res%5Cn%20%20%20%20%20%20%20%20%7D%5Cn%20%20%20%20%20%20%20%20if%20(count%20%3D%3D%3D%20len)%20%7B%5Cn%20%20%20%20%20%20%20%20%5Ctresolve(result)%5Cn%20%20%20%20%20%20%20%20%7D%5Cn%20%20%20%20%20%20%7D).catch(err%20%3D%3E%20%7B%5Cn%20%20%20%20%20%20%5Ctcount%20%2B%3D%201%5Cn%20%20%20%20%20%20%20%20%2F%2F%20%E5%A4%B1%E8%B4%A5%E5%B1%9E%E6%80%A7%E8%AE%BE%E7%BD%AE%5Cn%20%20%20%20%20%20%20%20result%5Bi%5D%20%3D%20%7B%5Cn%20%20%20%20%20%20%20%20%5Ctstatus%3A%20'rejected'%2C%5Cn%20%20%20%20%20%20%20%20%20%20reason%3A%20err%5Cn%20%20%20%20%20%20%20%20%7D%5Cn%20%20%20%20%20%20%20%20if%20(count%20%3D%3D%3D%20len)%20%7B%5Cn%20%20%20%20%20%20%20%20%5Ctresolve(result)%5Cn%20%20%20%20%20%20%20%20%7D%5Cn%20%20%20%20%20%20%7D)%5Cn%20%20%20%20%7D)%5Cn%20%20%7D)%5Cn%7D%22%2C%22autoWrap%22%3Afalse%2C%22heightLimit%22%3Atrue%2C%22collapsed%22%3Afalse%2C%22name%22%3A%22%22%2C%22tabSize%22%3Anull%2C%22indentWithTab%22%3Afalse%2C%22lightLines%22%3A%5B%5D%2C%22foldLines%22%3A%5B%5D%2C%22theme%22%3A%22One%20Dark%20Pro%22%2C%22__spacing%22%3A%22both%22%2C%22id%22%3A%22lCmol%22%2C%22margin%22%3A%7B%22top%22%3Atrue%2C%22bottom%22%3Atrue%7D%7D\"></card><h2 data-lake-id=\"m5Trz\" id=\"m5Trz\"><span data-lake-id=\"u061f6cbe\" id=\"u061f6cbe\">Promise.race</span></h2><p data-lake-id=\"u9d03eb9f\" id=\"u9d03eb9f\"><span data-lake-id=\"uddc25bbb\" id=\"uddc25bbb\">传入的所有实例哪一个实例的状态率先改变，那么就会返回哪个实例的返回值。无论成功还是失败</span></p><card type=\"inline\" name=\"codeblock\" value=\"data:%7B%22mode%22%3A%22javascript%22%2C%22code%22%3A%22Promise.prototype.race%20%3D%20promises%20%3D%3E%20%7B%5Cn%5Ctreturn%20new%20Promise((resolve%2C%20reject)%20%3D%3E%20%7B%5Cn%20%20%5Ctpromises.forEach(item%20%3D%3E%20%7B%5Cn%20%20%5Ct%5Ct%2F%2F%20%E6%AD%A4%E5%A4%84%E9%9C%80%E8%A6%81%E5%81%9A%E4%BA%8C%E6%AC%A1%E5%8C%85%E8%A3%85%EF%BC%8C%E9%98%B2%E6%AD%A2%E9%9D%9E%20Promise%20%E5%AF%B9%E8%B1%A1%5Cn%20%20%20%20%20%20%2F%2F%20%E5%90%8C%E6%97%B6%E8%BF%9B%E8%A1%8C%E7%8A%B6%E6%80%81%E7%9B%91%E5%90%AC%5Cn%20%20%20%20%20%20Promise.resolve(item)%5Cn%20%20%20%20%20%20%20%20.then(value%20%3D%3E%20resolve(value))%5Cn%20%20%20%20%20%20%20%20.catch(err%20%3D%3E%20reject(err))%5Cn%20%20%5Ct%7D)%5Cn%20%20%7D)%5Cn%7D%22%2C%22autoWrap%22%3Afalse%2C%22heightLimit%22%3Atrue%2C%22collapsed%22%3Afalse%2C%22name%22%3A%22%22%2C%22tabSize%22%3Anull%2C%22indentWithTab%22%3Afalse%2C%22lightLines%22%3A%5B%5D%2C%22foldLines%22%3A%5B%5D%2C%22theme%22%3A%22One%20Dark%20Pro%22%2C%22__spacing%22%3A%22both%22%2C%22id%22%3A%22CMLgZ%22%2C%22margin%22%3A%7B%22top%22%3Atrue%2C%22bottom%22%3Atrue%7D%7D\"></card><h2 data-lake-id=\"jdISu\" id=\"jdISu\"><span data-lake-id=\"u70a422b4\" id=\"u70a422b4\">Promise.any</span></h2><p data-lake-id=\"u44584718\" id=\"u44584718\"><span data-lake-id=\"ub9b16917\" id=\"ub9b16917\">只有全部实例都失败后才会返回失败，如果有一个实例的状态返回成功，则返回第一个成功的实例</span></p><card type=\"inline\" name=\"codeblock\" value=\"data:%7B%22mode%22%3A%22javascript%22%2C%22code%22%3A%22Promise.prototype.any%20%3D%20promises%20%3D%3E%20%7B%5Cn%20%20return%20new%20Promise((resolve%2C%20reject)%20%3D%3E%20%7B%5Cn%20%20%20%20let%20count%20%3D%200%5Cn%20%20%5Ctlet%20len%20%3D%20promiseList.length%5Cn%20%20%20%20if%20(len%20%3D%3D%3D%200)%20return%5Cn%20%20%20%20promises.forEach(item%20%3D%3E%20%7B%5Cn%20%20%20%20%5CtPromise.resolve(item)%5Cn%20%20%20%20%20%20%5Ct.then(value%20%3D%3E%20resolve(value))%5Cn%20%20%20%20%20%20%5Ct.catch(err%20%3D%3E%20%7B%5Cn%20%20%20%20%20%20%5Ct%5Ctcount%2B%3D1%5Cn%20%20%20%20%20%20%20%20%5Ctif%20(count%20%3D%3D%3D%20len)%20%7B%5Cn%20%20%20%20%20%20%20%20%20%20%5Ctreturn%20reject(new%20Error('All%20promises%20where%20rejected'))%5Cn%20%20%20%20%20%20%20%20%20%20%7D%5Cn%20%20%20%20%20%20%5Ct%7D)%5Cn%20%20%20%20%7D)%5Cn%20%20%7D)%5Cn%7D%22%2C%22autoWrap%22%3Afalse%2C%22heightLimit%22%3Atrue%2C%22collapsed%22%3Afalse%2C%22name%22%3A%22%22%2C%22tabSize%22%3Anull%2C%22indentWithTab%22%3Afalse%2C%22lightLines%22%3A%5B%5D%2C%22foldLines%22%3A%5B%5D%2C%22theme%22%3A%22One%20Dark%20Pro%22%2C%22__spacing%22%3A%22both%22%2C%22id%22%3A%22r6Eol%22%2C%22margin%22%3A%7B%22top%22%3Atrue%2C%22bottom%22%3Atrue%7D%7D\"></card>",
  "public": 0,
  "status": 1,
  "likes_count": 0,
  "read_count": 0,
  "hits": 0,
  "comments_count": 0,
  "word_count": 662,
  "created_at": "2022-05-11T15:01:35.000Z",
  "updated_at": "2022-05-11T15:08:08.000Z",
  "content_updated_at": "2022-05-11T15:01:35.000Z",
  "published_at": "2022-05-11T15:01:35.000Z",
  "first_published_at": "2022-05-11T15:01:34.833Z",
  "book": {
    "id": 27818302,
    "type": "Book",
    "slug": "pgkpvh",
    "name": "前端面试知识梳理",
    "user_id": 732231,
    "description": "",
    "toc_yml": "- type: META\n  count: 74\n  display_level: 1\n  tail_type: UPDATED_AT\n  base_version_id: 203636985\n  published: true\n  max_level: 1\n  last_updated_at: 2022-05-11T15:02:51.310Z\n  version_id: 203637675\n- type: TITLE\n  title: 基础 api 实现\n  uuid: 8cOHMB0GUaMGEJAZ\n  url: ''\n  prev_uuid: ''\n  sibling_uuid: XzzPhY1bnt-jy6Uq\n  child_uuid: tkSYK-Ar5LWNbwCs\n  parent_uuid: ''\n  doc_id: ''\n  level: 0\n  id: ''\n  open_window: 1\n  visible: 1\n- type: DOC\n  title: 实现 es6 的 extends\n  uuid: tkSYK-Ar5LWNbwCs\n  url: vtqbgk\n  prev_uuid: 8cOHMB0GUaMGEJAZ\n  sibling_uuid: iZbjvIrZWQPncGf4\n  child_uuid: ''\n  parent_uuid: 8cOHMB0GUaMGEJAZ\n  doc_id: 77021830\n  level: 1\n  id: 77021830\n  open_window: 0\n  visible: 1\n- type: DOC\n  title: 实现 ajax\n  uuid: iZbjvIrZWQPncGf4\n  url: cq5ws4\n  prev_uuid: tkSYK-Ar5LWNbwCs\n  sibling_uuid: GQ98GFTcsA6oX5fu\n  child_uuid: ''\n  parent_uuid: 8cOHMB0GUaMGEJAZ\n  doc_id: 77021696\n  level: 1\n  id: 77021696\n  open_window: 0\n  visible: 1\n- type: DOC\n  title: 实现 call、apply、bind\n  uuid: GQ98GFTcsA6oX5fu\n  url: ybrsyw\n  prev_uuid: iZbjvIrZWQPncGf4\n  sibling_uuid: 8mxtq-HrdjGBfE1K\n  child_uuid: ''\n  parent_uuid: 8cOHMB0GUaMGEJAZ\n  doc_id: 77021715\n  level: 1\n  id: 77021715\n  open_window: 0\n  visible: 1\n- type: DOC\n  title: 实现 new 关键字\n  uuid: 8mxtq-HrdjGBfE1K\n  url: pldu2b\n  prev_uuid: GQ98GFTcsA6oX5fu\n  sibling_uuid: DTHsD8sppgSTGUG-\n  child_uuid: ''\n  parent_uuid: 8cOHMB0GUaMGEJAZ\n  doc_id: 77021706\n  level: 1\n  id: 77021706\n  open_window: 0\n  visible: 1\n- type: DOC\n  title: 函数柯理化\n  uuid: DTHsD8sppgSTGUG-\n  url: yo9cx5\n  prev_uuid: 8mxtq-HrdjGBfE1K\n  sibling_uuid: TaRHTWpqD3Ef8QHU\n  child_uuid: ''\n  parent_uuid: 8cOHMB0GUaMGEJAZ\n  doc_id: 77021634\n  level: 1\n  id: 77021634\n  open_window: 0\n  visible: 1\n- type: DOC\n  title: 浅拷贝和深拷贝\n  uuid: TaRHTWpqD3Ef8QHU\n  url: ufks1z\n  prev_uuid: DTHsD8sppgSTGUG-\n  sibling_uuid: 4Z30CA9ZXVdeKnnL\n  child_uuid: ''\n  parent_uuid: 8cOHMB0GUaMGEJAZ\n  doc_id: 77021640\n  level: 1\n  id: 77021640\n  open_window: 0\n  visible: 1\n- type: DOC\n  title: 实现 instanceof\n  uuid: 4Z30CA9ZXVdeKnnL\n  url: ba4wuo\n  prev_uuid: TaRHTWpqD3Ef8QHU\n  sibling_uuid: 2MBif8wnmvigRAxT\n  child_uuid: ''\n  parent_uuid: 8cOHMB0GUaMGEJAZ\n  doc_id: 77021689\n  level: 1\n  id: 77021689\n  open_window: 0\n  visible: 1\n- type: DOC\n  title: 手动实现定时器\n  uuid: 2MBif8wnmvigRAxT\n  url: wf9bwg\n  prev_uuid: 4Z30CA9ZXVdeKnnL\n  sibling_uuid: 8f6jGaWidUBFSNN7\n  child_uuid: ''\n  parent_uuid: 8cOHMB0GUaMGEJAZ\n  doc_id: 77021645\n  level: 1\n  id: 77021645\n  open_window: 0\n  visible: 1\n- type: DOC\n  title: sleep 函数实现\n  uuid: 8f6jGaWidUBFSNN7\n  url: ngwrak\n  prev_uuid: 2MBif8wnmvigRAxT\n  sibling_uuid: lXeuN-kwl51AKTO0\n  child_uuid: ''\n  parent_uuid: 8cOHMB0GUaMGEJAZ\n  doc_id: 77021787\n  level: 1\n  id: 77021787\n  open_window: 0\n  visible: 1\n- type: DOC\n  title: 实现 JSON.stringify\n  uuid: lXeuN-kwl51AKTO0\n  url: mtoe2n\n  prev_uuid: 8f6jGaWidUBFSNN7\n  sibling_uuid: hVvT5-pJ5qVvYNrK\n  child_uuid: ''\n  parent_uuid: 8cOHMB0GUaMGEJAZ\n  doc_id: 77021785\n  level: 1\n  id: 77021785\n  open_window: 0\n  visible: 1\n- type: DOC\n  title: js 通用类型获取\n  uuid: hVvT5-pJ5qVvYNrK\n  url: tll6lm\n  prev_uuid: lXeuN-kwl51AKTO0\n  sibling_uuid: ''\n  child_uuid: ''\n  parent_uuid: 8cOHMB0GUaMGEJAZ\n  doc_id: 77021802\n  level: 1\n  id: 77021802\n  open_window: 0\n  visible: 1\n- type: TITLE\n  title: 防抖和节流\n  uuid: XzzPhY1bnt-jy6Uq\n  url: ''\n  prev_uuid: 8cOHMB0GUaMGEJAZ\n  sibling_uuid: PkyQAjgp1TOfRd_2\n  child_uuid: AQvBtgwRPd2U2nSA\n  parent_uuid: ''\n  doc_id: ''\n  level: 0\n  id: ''\n  open_window: 1\n  visible: 1\n- type: DOC\n  title: 防抖\n  uuid: AQvBtgwRPd2U2nSA\n  url: enlngv\n  prev_uuid: XzzPhY1bnt-jy6Uq\n  sibling_uuid: nlhlSMjYGwG8o1jH\n  child_uuid: ''\n  parent_uuid: XzzPhY1bnt-jy6Uq\n  doc_id: 77021614\n  level: 1\n  id: 77021614\n  open_window: 0\n  visible: 1\n- type: DOC\n  title: 节流\n  uuid: nlhlSMjYGwG8o1jH\n  url: griz0t\n  prev_uuid: AQvBtgwRPd2U2nSA\n  sibling_uuid: ''\n  child_uuid: ''\n  parent_uuid: XzzPhY1bnt-jy6Uq\n  doc_id: 77021626\n  level: 1\n  id: 77021626\n  open_window: 0\n  visible: 1\n- type: TITLE\n  title: 数组相关\n  uuid: PkyQAjgp1TOfRd_2\n  url: ''\n  prev_uuid: XzzPhY1bnt-jy6Uq\n  sibling_uuid: 5NjAYoIgV-DfXemF\n  child_uuid: xTSsZIKFI9Di3LBH\n  parent_uuid: ''\n  doc_id: ''\n  level: 0\n  id: ''\n  open_window: 1\n  visible: 1\n- type: DOC\n  title: 数组转树\n  uuid: xTSsZIKFI9Di3LBH\n  url: bzgequ\n  prev_uuid: PkyQAjgp1TOfRd_2\n  sibling_uuid: Z_6uIAB9XA6raQPD\n  child_uuid: ''\n  parent_uuid: PkyQAjgp1TOfRd_2\n  doc_id: 77021833\n  level: 1\n  id: 77021833\n  open_window: 0\n  visible: 0\n- type: DOC\n  title: 树转数组\n  uuid: Z_6uIAB9XA6raQPD\n  url: xycpzl\n  prev_uuid: xTSsZIKFI9Di3LBH\n  sibling_uuid: hoLauQ33F3aF2wq7\n  child_uuid: ''\n  parent_uuid: PkyQAjgp1TOfRd_2\n  doc_id: 77021835\n  level: 1\n  id: 77021835\n  open_window: 0\n  visible: 1\n- type: DOC\n  title: 数组常用方法\n  uuid: hoLauQ33F3aF2wq7\n  url: owtewn\n  prev_uuid: Z_6uIAB9XA6raQPD\n  sibling_uuid: rvc_A-WMsWds7EBa\n  child_uuid: ''\n  parent_uuid: PkyQAjgp1TOfRd_2\n  doc_id: 77021725\n  level: 1\n  id: 77021725\n  open_window: 0\n  visible: 1\n- type: DOC\n  title: 数组去重实现\n  uuid: rvc_A-WMsWds7EBa\n  url: gq2z9n\n  prev_uuid: hoLauQ33F3aF2wq7\n  sibling_uuid: NB4bY-etxMWq1YWS\n  child_uuid: ''\n  parent_uuid: PkyQAjgp1TOfRd_2\n  doc_id: 77021623\n  level: 1\n  id: 77021623\n  open_window: 0\n  visible: 1\n- type: DOC\n  title: 数组扁平化实现\n  uuid: NB4bY-etxMWq1YWS\n  url: doeryg\n  prev_uuid: rvc_A-WMsWds7EBa\n  sibling_uuid: DBoiy0L7Hhm_Zrkf\n  child_uuid: ''\n  parent_uuid: PkyQAjgp1TOfRd_2\n  doc_id: 77021607\n  level: 1\n  id: 77021607\n  open_window: 0\n  visible: 1\n- type: DOC\n  title: 类数组转换为数组\n  uuid: DBoiy0L7Hhm_Zrkf\n  url: csgagn\n  prev_uuid: NB4bY-etxMWq1YWS\n  sibling_uuid: E4WkD_rpaai_v3HK\n  child_uuid: ''\n  parent_uuid: PkyQAjgp1TOfRd_2\n  doc_id: 77021754\n  level: 1\n  id: 77021754\n  open_window: 0\n  visible: 1\n- type: DOC\n  title: 实现数组乱序输出\n  uuid: E4WkD_rpaai_v3HK\n  url: xlrgnu\n  prev_uuid: DBoiy0L7Hhm_Zrkf\n  sibling_uuid: OkcuvyhOMA6N0ex4\n  child_uuid: ''\n  parent_uuid: PkyQAjgp1TOfRd_2\n  doc_id: 77021731\n  level: 1\n  id: 77021731\n  open_window: 0\n  visible: 1\n- type: DOC\n  title: 查找二维数组的目标值\n  uuid: OkcuvyhOMA6N0ex4\n  url: tmw2ny\n  prev_uuid: E4WkD_rpaai_v3HK\n  sibling_uuid: F8K4-6VRqHrupctd\n  child_uuid: ''\n  parent_uuid: PkyQAjgp1TOfRd_2\n  doc_id: 77021789\n  level: 1\n  id: 77021789\n  open_window: 0\n  visible: 1\n- type: DOC\n  title: 二维数组斜向打印\n  uuid: F8K4-6VRqHrupctd\n  url: aqw6my\n  prev_uuid: OkcuvyhOMA6N0ex4\n  sibling_uuid: ''\n  child_uuid: ''\n  parent_uuid: PkyQAjgp1TOfRd_2\n  doc_id: 77021780\n  level: 1\n  id: 77021780\n  open_window: 0\n  visible: 1\n- type: TITLE\n  title: 字符串相关\n  uuid: 5NjAYoIgV-DfXemF\n  url: ''\n  prev_uuid: PkyQAjgp1TOfRd_2\n  sibling_uuid: Q34_kLhQ_uWoQw46\n  child_uuid: XNjX12HqmJBUHjy7\n  parent_uuid: ''\n  doc_id: ''\n  level: 0\n  id: ''\n  open_window: 1\n  visible: 1\n- type: DOC\n  title: 实现字符串的 repeat 方法\n  uuid: XNjX12HqmJBUHjy7\n  url: hxelqc\n  prev_uuid: 5NjAYoIgV-DfXemF\n  sibling_uuid: ''\n  child_uuid: ''\n  parent_uuid: 5NjAYoIgV-DfXemF\n  doc_id: 77021740\n  level: 1\n  id: 77021740\n  open_window: 0\n  visible: 1\n- type: TITLE\n  title: promise相关\n  uuid: Q34_kLhQ_uWoQw46\n  url: ''\n  prev_uuid: 5NjAYoIgV-DfXemF\n  sibling_uuid: aXqdYGJNJ1HlijwX\n  child_uuid: fuTj4su1VjBeHDO5\n  parent_uuid: ''\n  doc_id: ''\n  level: 0\n  id: ''\n  open_window: 1\n  visible: 1\n- type: DOC\n  title: 实现 Promise A+\n  uuid: fuTj4su1VjBeHDO5\n  url: fl6cgx\n  prev_uuid: Q34_kLhQ_uWoQw46\n  sibling_uuid: IOPLb2N42d3OZ0Zq\n  child_uuid: ''\n  parent_uuid: Q34_kLhQ_uWoQw46\n  doc_id: 77021620\n  level: 1\n  id: 77021620\n  open_window: 0\n  visible: 1\n- type: DOC\n  title: Promise  常用方法实现\n  uuid: IOPLb2N42d3OZ0Zq\n  url: vd2h4l\n  prev_uuid: fuTj4su1VjBeHDO5\n  sibling_uuid: vKLkkDq-XoJwsqMW\n  child_uuid: ''\n  parent_uuid: Q34_kLhQ_uWoQw46\n  doc_id: 77021632\n  level: 1\n  id: 77021632\n  open_window: 0\n  visible: 1\n- type: DOC\n  title: Promise 并发控制\n  uuid: vKLkkDq-XoJwsqMW\n  url: gd3193\n  prev_uuid: IOPLb2N42d3OZ0Zq\n  sibling_uuid: rYJ2dherst1MyK0I\n  child_uuid: ''\n  parent_uuid: Q34_kLhQ_uWoQw46\n  doc_id: 77021662\n  level: 1\n  id: 77021662\n  open_window: 0\n  visible: 1\n- type: DOC\n  title: Promise 缓存\n  uuid: rYJ2dherst1MyK0I\n  url: sgcusf\n  prev_uuid: vKLkkDq-XoJwsqMW\n  sibling_uuid: xZ5UrxtCjhBJxiXK\n  child_uuid: ''\n  parent_uuid: Q34_kLhQ_uWoQw46\n  doc_id: 77021679\n  level: 1\n  id: 77021679\n  open_window: 0\n  visible: 1\n- type: DOC\n  title: 异步串行输出\n  uuid: xZ5UrxtCjhBJxiXK\n  url: um4g6z\n  prev_uuid: rYJ2dherst1MyK0I\n  sibling_uuid: fZuICDZLsFJSo57b\n  child_uuid: ''\n  parent_uuid: Q34_kLhQ_uWoQw46\n  doc_id: 77021649\n  level: 1\n  id: 77021649\n  open_window: 0\n  visible: 1\n- type: DOC\n  title: 带并发的异步调度器 Scheduler\n  uuid: fZuICDZLsFJSo57b\n  url: kbkc8e\n  prev_uuid: xZ5UrxtCjhBJxiXK\n  sibling_uuid: ''\n  child_uuid: ''\n  parent_uuid: Q34_kLhQ_uWoQw46\n  doc_id: 77021700\n  level: 1\n  id: 77021700\n  open_window: 0\n  visible: 1\n- type: TITLE\n  title: 数据处理\n  uuid: aXqdYGJNJ1HlijwX\n  url: ''\n  prev_uuid: Q34_kLhQ_uWoQw46\n  sibling_uuid: oj23-2V9egz1L0Ic\n  child_uuid: SxxBIhY4HFEaNF8V\n  parent_uuid: ''\n  doc_id: ''\n  level: 0\n  id: ''\n  open_window: 1\n  visible: 1\n- type: DOC\n  title: 解析 url 参数对象\n  uuid: SxxBIhY4HFEaNF8V\n  url: rxw8qp\n  prev_uuid: aXqdYGJNJ1HlijwX\n  sibling_uuid: yiD9ldSpBGzQNQxQ\n  child_uuid: ''\n  parent_uuid: aXqdYGJNJ1HlijwX\n  doc_id: 77021764\n  level: 1\n  id: 77021764\n  open_window: 0\n  visible: 1\n- type: DOC\n  title: 实现日期格式化函数\n  uuid: yiD9ldSpBGzQNQxQ\n  url: shzfyg\n  prev_uuid: SxxBIhY4HFEaNF8V\n  sibling_uuid: _3QVaw5COwwvCXZv\n  child_uuid: ''\n  parent_uuid: aXqdYGJNJ1HlijwX\n  doc_id: 77021710\n  level: 1\n  id: 77021710\n  open_window: 0\n  visible: 1\n- type: DOC\n  title: 交换 a、b 的值，不使用临时变量\n  uuid: _3QVaw5COwwvCXZv\n  url: xw17tv\n  prev_uuid: yiD9ldSpBGzQNQxQ\n  sibling_uuid: Mq5fe2v7j2INDdvL\n  child_uuid: ''\n  parent_uuid: aXqdYGJNJ1HlijwX\n  doc_id: 77021736\n  level: 1\n  id: 77021736\n  open_window: 0\n  visible: 1\n- type: DOC\n  title: 获取两个数之间的任意随机数\n  uuid: Mq5fe2v7j2INDdvL\n  url: vhngph\n  prev_uuid: _3QVaw5COwwvCXZv\n  sibling_uuid: 8Chl_bOMaALA1jhP\n  child_uuid: ''\n  parent_uuid: aXqdYGJNJ1HlijwX\n  doc_id: 77021688\n  level: 1\n  id: 77021688\n  open_window: 0\n  visible: 1\n- type: DOC\n  title: 将数字千分位用逗号隔开\n  uuid: 8Chl_bOMaALA1jhP\n  url: vphpea\n  prev_uuid: Mq5fe2v7j2INDdvL\n  sibling_uuid: MLI7v9Et4dIn7XiV\n  child_uuid: ''\n  parent_uuid: aXqdYGJNJ1HlijwX\n  doc_id: 77021743\n  level: 1\n  id: 77021743\n  open_window: 0\n  visible: 1\n- type: DOC\n  title: 实现非负大整数相加\n  uuid: MLI7v9Et4dIn7XiV\n  url: xlvd0g\n  prev_uuid: 8Chl_bOMaALA1jhP\n  sibling_uuid: mVWcb08QaDpa9PNH\n  child_uuid: ''\n  parent_uuid: aXqdYGJNJ1HlijwX\n  doc_id: 77021748\n  level: 1\n  id: 77021748\n  open_window: 0\n  visible: 1\n- type: DOC\n  title: 判断对象是否存在循环引用\n  uuid: mVWcb08QaDpa9PNH\n  url: phqdmd\n  prev_uuid: MLI7v9Et4dIn7XiV\n  sibling_uuid: ''\n  child_uuid: ''\n  parent_uuid: aXqdYGJNJ1HlijwX\n  doc_id: 77021768\n  level: 1\n  id: 77021768\n  open_window: 0\n  visible: 1\n- type: TITLE\n  title: 框架\n  uuid: oj23-2V9egz1L0Ic\n  url: ''\n  prev_uuid: aXqdYGJNJ1HlijwX\n  sibling_uuid: BTeDPodj0NU8fRW3\n  child_uuid: t5HRubL3aXPLNoG6\n  parent_uuid: ''\n  doc_id: ''\n  level: 0\n  id: ''\n  open_window: 1\n  visible: 1\n- type: DOC\n  title: 发布订阅模式\n  uuid: t5HRubL3aXPLNoG6\n  url: ezcdgo\n  prev_uuid: oj23-2V9egz1L0Ic\n  sibling_uuid: EqMT4jazWkuKJX1v\n  child_uuid: ''\n  parent_uuid: oj23-2V9egz1L0Ic\n  doc_id: 77021611\n  level: 1\n  id: 77021611\n  open_window: 0\n  visible: 1\n- type: DOC\n  title: 观察者模式\n  uuid: EqMT4jazWkuKJX1v\n  url: dwziom\n  prev_uuid: t5HRubL3aXPLNoG6\n  sibling_uuid: O5OEkYSpde-8we8V\n  child_uuid: ''\n  parent_uuid: oj23-2V9egz1L0Ic\n  doc_id: 77021795\n  level: 1\n  id: 77021795\n  open_window: 0\n  visible: 1\n- type: DOC\n  title: 简易版 vue2\n  uuid: O5OEkYSpde-8we8V\n  url: indxog\n  prev_uuid: EqMT4jazWkuKJX1v\n  sibling_uuid: XOQaAmtLM_gvM85t\n  child_uuid: ''\n  parent_uuid: oj23-2V9egz1L0Ic\n  doc_id: 77021636\n  level: 1\n  id: 77021636\n  open_window: 0\n  visible: 1\n- type: DOC\n  title: 简易版 vue3\n  uuid: XOQaAmtLM_gvM85t\n  url: an017i\n  prev_uuid: O5OEkYSpde-8we8V\n  sibling_uuid: ciSabdz5MTC1wbC7\n  child_uuid: ''\n  parent_uuid: oj23-2V9egz1L0Ic\n  doc_id: 77021804\n  level: 1\n  id: 77021804\n  open_window: 0\n  visible: 1\n- type: DOC\n  title: 简易版 vuex\n  uuid: ciSabdz5MTC1wbC7\n  url: myzomg\n  prev_uuid: XOQaAmtLM_gvM85t\n  sibling_uuid: ''\n  child_uuid: ''\n  parent_uuid: oj23-2V9egz1L0Ic\n  doc_id: 77021704\n  level: 1\n  id: 77021704\n  open_window: 0\n  visible: 1\n- type: TITLE\n  title: 应用场景\n  uuid: BTeDPodj0NU8fRW3\n  url: ''\n  prev_uuid: oj23-2V9egz1L0Ic\n  sibling_uuid: KKJ-BzUK3K9FxUJ2\n  child_uuid: U1oF7BfjBGNpWa79\n  parent_uuid: ''\n  doc_id: ''\n  level: 0\n  id: ''\n  open_window: 1\n  visible: 1\n- type: DOC\n  title: 通过调用 addRemote 实现 add\n  uuid: U1oF7BfjBGNpWa79\n  url: edff3s\n  prev_uuid: BTeDPodj0NU8fRW3\n  sibling_uuid: RMAn78BGFgyI8W6c\n  child_uuid: ''\n  parent_uuid: BTeDPodj0NU8fRW3\n  doc_id: 77021816\n  level: 1\n  id: 77021816\n  open_window: 0\n  visible: 1\n- type: DOC\n  title: 倒计时\n  uuid: RMAn78BGFgyI8W6c\n  url: uwleof\n  prev_uuid: U1oF7BfjBGNpWa79\n  sibling_uuid: aYlobR47xz0qHkhF\n  child_uuid: ''\n  parent_uuid: BTeDPodj0NU8fRW3\n  doc_id: 77021810\n  level: 1\n  id: 77021810\n  open_window: 0\n  visible: 1\n- type: DOC\n  title: 版本号比较\n  uuid: aYlobR47xz0qHkhF\n  url: cynvvd\n  prev_uuid: RMAn78BGFgyI8W6c\n  sibling_uuid: N0u_B_WnmtCeQwFI\n  child_uuid: ''\n  parent_uuid: BTeDPodj0NU8fRW3\n  doc_id: 77021792\n  level: 1\n  id: 77021792\n  open_window: 0\n  visible: 1\n- type: DOC\n  title: 实现简单路由\n  uuid: N0u_B_WnmtCeQwFI\n  url: zzc9k3\n  prev_uuid: aYlobR47xz0qHkhF\n  sibling_uuid: es8IUmiyOTWzwKa9\n  child_uuid: ''\n  parent_uuid: BTeDPodj0NU8fRW3\n  doc_id: 77021784\n  level: 1\n  id: 77021784\n  open_window: 0\n  visible: 1\n- type: DOC\n  title: 长列表虚拟滚动\n  uuid: es8IUmiyOTWzwKa9\n  url: wsmws7\n  prev_uuid: N0u_B_WnmtCeQwFI\n  sibling_uuid: yKn9f3BKX1S3tsyK\n  child_uuid: ''\n  parent_uuid: BTeDPodj0NU8fRW3\n  doc_id: 77021653\n  level: 1\n  id: 77021653\n  open_window: 0\n  visible: 1\n- type: DOC\n  title: 围圈报数问题\n  uuid: yKn9f3BKX1S3tsyK\n  url: gkoa19\n  prev_uuid: es8IUmiyOTWzwKa9\n  sibling_uuid: zmiKBP3HABO6Ig_9\n  child_uuid: ''\n  parent_uuid: BTeDPodj0NU8fRW3\n  doc_id: 77021761\n  level: 1\n  id: 77021761\n  open_window: 0\n  visible: 1\n- type: DOC\n  title: 查找文章中出现频率最高的词\n  uuid: zmiKBP3HABO6Ig_9\n  url: rln2y3\n  prev_uuid: yKn9f3BKX1S3tsyK\n  sibling_uuid: cDzdEkch3JypwTh2\n  child_uuid: ''\n  parent_uuid: BTeDPodj0NU8fRW3\n  doc_id: 77021772\n  level: 1\n  id: 77021772\n  open_window: 0\n  visible: 1\n- type: DOC\n  title: Promise 每隔 1s 输出 1、2、3\n  uuid: cDzdEkch3JypwTh2\n  url: yg55el\n  prev_uuid: zmiKBP3HABO6Ig_9\n  sibling_uuid: II7sWIfm_eSWwKfq\n  child_uuid: ''\n  parent_uuid: BTeDPodj0NU8fRW3\n  doc_id: 77021821\n  level: 1\n  id: 77021821\n  open_window: 0\n  visible: 1\n- type: DOC\n  title: 循环打印红黄绿\n  uuid: II7sWIfm_eSWwKfq\n  url: wyhgfz\n  prev_uuid: cDzdEkch3JypwTh2\n  sibling_uuid: 0hKcnD9qnLeCTq4Q\n  child_uuid: ''\n  parent_uuid: BTeDPodj0NU8fRW3\n  doc_id: 77021776\n  level: 1\n  id: 77021776\n  open_window: 0\n  visible: 1\n- type: DOC\n  title: 封装一个异步加载图片的方法\n  uuid: 0hKcnD9qnLeCTq4Q\n  url: orxq0m\n  prev_uuid: II7sWIfm_eSWwKfq\n  sibling_uuid: b7lf8zlMeqorWGgi\n  child_uuid: ''\n  parent_uuid: BTeDPodj0NU8fRW3\n  doc_id: 77021825\n  level: 1\n  id: 77021825\n  open_window: 0\n  visible: 1\n- type: DOC\n  title: 实现 mergePromise 函数\n  uuid: b7lf8zlMeqorWGgi\n  url: apqplp\n  prev_uuid: 0hKcnD9qnLeCTq4Q\n  sibling_uuid: EZZ2GBqZ-B1LUsam\n  child_uuid: ''\n  parent_uuid: BTeDPodj0NU8fRW3\n  doc_id: 77021819\n  level: 1\n  id: 77021819\n  open_window: 0\n  visible: 1\n- type: DOC\n  title: 图片加载数量限制\n  uuid: EZZ2GBqZ-B1LUsam\n  url: xz2gy5\n  prev_uuid: b7lf8zlMeqorWGgi\n  sibling_uuid: '-8N7uf1xcBmFXSQI'\n  child_uuid: ''\n  parent_uuid: BTeDPodj0NU8fRW3\n  doc_id: 77021664\n  level: 1\n  id: 77021664\n  open_window: 0\n  visible: 1\n- type: DOC\n  title: 文本中识别敏感词、表情包、链接、数字、字母并高亮\n  uuid: '-8N7uf1xcBmFXSQI'\n  url: athu4p\n  prev_uuid: EZZ2GBqZ-B1LUsam\n  sibling_uuid: F_Fz97LW3aSxLLnr\n  child_uuid: ''\n  parent_uuid: BTeDPodj0NU8fRW3\n  doc_id: 77021666\n  level: 1\n  id: 77021666\n  open_window: 0\n  visible: 1\n- type: DOC\n  title: 图片格式转换为 webp\n  uuid: F_Fz97LW3aSxLLnr\n  url: cwlftq\n  prev_uuid: '-8N7uf1xcBmFXSQI'\n  sibling_uuid: wfz5QMLK_eAEtlFz\n  child_uuid: ''\n  parent_uuid: BTeDPodj0NU8fRW3\n  doc_id: 77021647\n  level: 1\n  id: 77021647\n  open_window: 0\n  visible: 1\n- type: DOC\n  title: 计算对象占用的字节数\n  uuid: wfz5QMLK_eAEtlFz\n  url: gx1y1y\n  prev_uuid: F_Fz97LW3aSxLLnr\n  sibling_uuid: rKjJYSK4ytL18T9L\n  child_uuid: ''\n  parent_uuid: BTeDPodj0NU8fRW3\n  doc_id: 77021669\n  level: 1\n  id: 77021669\n  open_window: 0\n  visible: 1\n- type: DOC\n  title: 给 xhr 添加 hook，实现在各个阶段打印日志\n  uuid: rKjJYSK4ytL18T9L\n  url: dm9n4g\n  prev_uuid: wfz5QMLK_eAEtlFz\n  sibling_uuid: zZADZWaE-olCAOjQ\n  child_uuid: ''\n  parent_uuid: BTeDPodj0NU8fRW3\n  doc_id: 77021658\n  level: 1\n  id: 77021658\n  open_window: 0\n  visible: 1\n- type: DOC\n  title: 明信片问题\n  uuid: zZADZWaE-olCAOjQ\n  url: mnsw3z\n  prev_uuid: rKjJYSK4ytL18T9L\n  sibling_uuid: ''\n  child_uuid: ''\n  parent_uuid: BTeDPodj0NU8fRW3\n  doc_id: 77021807\n  level: 1\n  id: 77021807\n  open_window: 0\n  visible: 1\n- type: TITLE\n  title: 常用算法实现\n  uuid: KKJ-BzUK3K9FxUJ2\n  url: ''\n  prev_uuid: BTeDPodj0NU8fRW3\n  sibling_uuid: ''\n  child_uuid: z8xQMUujFU-0OTsg\n  parent_uuid: ''\n  doc_id: ''\n  level: 0\n  id: ''\n  open_window: 1\n  visible: 1\n- type: DOC\n  title: 二分查找\n  uuid: z8xQMUujFU-0OTsg\n  url: pywta0\n  prev_uuid: KKJ-BzUK3K9FxUJ2\n  sibling_uuid: _b3VVGX3aAQ_rvuS\n  child_uuid: ''\n  parent_uuid: KKJ-BzUK3K9FxUJ2\n  doc_id: 77021798\n  level: 1\n  id: 77021798\n  open_window: 0\n  visible: 1\n- type: DOC\n  title: 排序\n  uuid: _b3VVGX3aAQ_rvuS\n  url: ivvld9\n  prev_uuid: z8xQMUujFU-0OTsg\n  sibling_uuid: eRQoWM79y_Mwbg2D\n  child_uuid: ''\n  parent_uuid: KKJ-BzUK3K9FxUJ2\n  doc_id: 77021670\n  level: 1\n  id: 77021670\n  open_window: 0\n  visible: 1\n- type: DOC\n  title: 动态规划和贪心算法\n  uuid: eRQoWM79y_Mwbg2D\n  url: pyig7m\n  prev_uuid: _b3VVGX3aAQ_rvuS\n  sibling_uuid: tr1DuV5ACUbyp8j-\n  child_uuid: ''\n  parent_uuid: KKJ-BzUK3K9FxUJ2\n  doc_id: 77021676\n  level: 1\n  id: 77021676\n  open_window: 0\n  visible: 1\n- type: DOC\n  title: 洗牌算法\n  uuid: tr1DuV5ACUbyp8j-\n  url: tohw0k\n  prev_uuid: eRQoWM79y_Mwbg2D\n  sibling_uuid: x9xEaoi_A59UZjS5\n  child_uuid: ''\n  parent_uuid: KKJ-BzUK3K9FxUJ2\n  doc_id: 77021687\n  level: 1\n  id: 77021687\n  open_window: 0\n  visible: 1\n- type: DOC\n  title: LRU(最少置换算法)\n  uuid: x9xEaoi_A59UZjS5\n  url: tmwgql\n  prev_uuid: tr1DuV5ACUbyp8j-\n  sibling_uuid: XsgMUe05eXycAX93\n  child_uuid: ''\n  parent_uuid: KKJ-BzUK3K9FxUJ2\n  doc_id: 77021694\n  level: 1\n  id: 77021694\n  open_window: 0\n  visible: 1\n- type: DOC\n  title: 斐波那契数列\n  uuid: XsgMUe05eXycAX93\n  url: bq7f7e\n  prev_uuid: x9xEaoi_A59UZjS5\n  sibling_uuid: T0orOt1CWhzdAczU\n  child_uuid: ''\n  parent_uuid: KKJ-BzUK3K9FxUJ2\n  doc_id: 77021683\n  level: 1\n  id: 77021683\n  open_window: 0\n  visible: 1\n- type: DOC\n  title: 大数相加\n  uuid: T0orOt1CWhzdAczU\n  url: ln6fpo\n  prev_uuid: XsgMUe05eXycAX93\n  sibling_uuid: ''\n  child_uuid: ''\n  parent_uuid: KKJ-BzUK3K9FxUJ2\n  doc_id: 77021693\n  level: 1\n  id: 77021693\n  open_window: 0\n  visible: 1\n",
    "creator_id": 732231,
    "public": 0,
    "items_count": 65,
    "likes_count": 0,
    "watches_count": 1,
    "content_updated_at": "2023-01-06T09:17:32.188Z",
    "created_at": "2022-05-11T14:43:59.000Z",
    "updated_at": "2023-11-11T18:10:33.000Z",
    "user": {
      "id": 732231,
      "type": "User",
      "login": "wcywxq",
      "name": "magic",
      "avatar_url": "https://cdn.nlark.com/yuque/0/2020/png/732231/1606968271774-avatar/886ad88b-d2cc-4c9e-a674-f70eb51a679c.png",
      "books_count": 21,
      "public_books_count": 0,
      "followers_count": 0,
      "following_count": 0,
      "public": 1,
      "description": null,
      "created_at": "2020-01-08T14:21:31.000Z",
      "updated_at": "2023-11-22T20:13:30.000Z",
      "work_id": "",
      "_serializer": "v2.user"
    },
    "namespace": "wcywxq/pgkpvh",
    "_serializer": "v2.book"
  },
  "user": {
    "id": 732231,
    "type": "User",
    "login": "wcywxq",
    "name": "magic",
    "avatar_url": "https://cdn.nlark.com/yuque/0/2020/png/732231/1606968271774-avatar/886ad88b-d2cc-4c9e-a674-f70eb51a679c.png",
    "books_count": 21,
    "public_books_count": 0,
    "followers_count": 0,
    "following_count": 0,
    "public": 1,
    "description": null,
    "created_at": "2020-01-08T14:21:31.000Z",
    "updated_at": "2023-11-22T20:13:30.000Z",
    "work_id": "",
    "_serializer": "v2.user"
  },
  "tags": [],
  "latest_version_id": 984848572,
  "creator": {
    "id": 732231,
    "type": "User",
    "login": "wcywxq",
    "name": "magic",
    "avatar_url": "https://cdn.nlark.com/yuque/0/2020/png/732231/1606968271774-avatar/886ad88b-d2cc-4c9e-a674-f70eb51a679c.png",
    "books_count": 21,
    "public_books_count": 0,
    "followers_count": 0,
    "following_count": 0,
    "public": 1,
    "description": null,
    "created_at": "2020-01-08T14:21:31.000Z",
    "updated_at": "2023-11-22T20:13:30.000Z",
    "work_id": "",
    "_serializer": "v2.user"
  },
  "_serializer": "v2.doc_detail"
}