{
  "id": 72212442,
  "slug": "xlvd0g",
  "title": "实现非负大整数相加",
  "book_id": 26225252,
  "book": {
    "id": 26225252,
    "type": "Book",
    "slug": "sd8kbc",
    "name": "笔试 written test",
    "user_id": 732231,
    "description": "笔试相关题目\n1. 原生 API 实现\n2. 业务场景相关问题\n3. LeetCode 算法相关问题",
    "creator_id": 732231,
    "public": 0,
    "items_count": 74,
    "likes_count": 0,
    "watches_count": 1,
    "content_updated_at": "2023-11-11T18:15:38.713Z",
    "updated_at": "2023-11-11T18:15:39.000Z",
    "created_at": "2022-04-04T11:34:53.000Z",
    "namespace": "wcywxq/sd8kbc",
    "user": {
      "id": 732231,
      "type": "User",
      "login": "wcywxq",
      "name": "magic",
      "description": null,
      "avatar_url": "https://cdn.nlark.com/yuque/0/2020/png/732231/1606968271774-avatar/886ad88b-d2cc-4c9e-a674-f70eb51a679c.png",
      "books_count": 18,
      "public_books_count": 0,
      "followers_count": 0,
      "following_count": 0,
      "created_at": "2020-01-08T14:21:31.000Z",
      "updated_at": "2023-11-13T09:32:35.000Z",
      "_serializer": "v2.user"
    },
    "_serializer": "v2.book"
  },
  "user_id": 732231,
  "creator": {
    "id": 732231,
    "type": "User",
    "login": "wcywxq",
    "name": "magic",
    "description": null,
    "avatar_url": "https://cdn.nlark.com/yuque/0/2020/png/732231/1606968271774-avatar/886ad88b-d2cc-4c9e-a674-f70eb51a679c.png",
    "books_count": 18,
    "public_books_count": 0,
    "followers_count": 0,
    "following_count": 0,
    "created_at": "2020-01-08T14:21:31.000Z",
    "updated_at": "2023-11-13T09:32:35.000Z",
    "_serializer": "v2.user"
  },
  "format": "lake",
  "body": "```javascript\nNumber.MAX_VALUE // 1.7976931348623157e+308\nNumber.MAX_SAFE_INTEGER // 9007199254740991\nNumber.MIN_VALUE // 5e-324\nNumber.MIN_SAFE_INTEGER // -9007199254740991\n```\n如果想要对一个超大的整数(`> Number.MAX_SAFE_INTEGER`)进行加法运算，但是又想输出一般形式，那么使用 + 是无法达到的，一旦数字超过 `Number.MAX_SAFE_INTEGER` 数字会被立即转换为科学计数法，并且数字精度相比以前将会有误差。\n<a name=\"Isqf4\"></a>\n## 利用算法实现大数相加\n<a name=\"RxDUt\"></a>\n### 主要思路\n\n- 首先用字符串的方式来保存大数，这样数字在数学表示上就不会发生变化\n- 初始化 `res`，`temp` 来保存中间的计算结果，并将两个字符串转化为数组，以便进行每一位的加法运算\n- 将两个数组的对应的位进行相加，两个数相加的结果可能大于 `10`，所以可能要仅为，对 `10` 进行取余操作，将结果保存在当前位\n- 判断当前位是否大于 `9`，也就是是否会进位，若是则将 `temp` 赋值为 `true`，因为在加法运算中，`true` 会自动隐式转化为 `1`，以便于下一次相加\n- 重复上述操作，直至计算结束\n<a name=\"pVVrc\"></a>\n### 实现\n```javascript\nfunction sumBigNumebr(a, b) {\n\tlet res = ''\n  let temp = 0\n  a = a.split('')\n  b = b.split('')\n  \n  while(a.length || b.length || temp) {\n  \ttemp += ~~a.pop() + ~~b.pop()\n    res = res + (temp % 10)\n    temp = temp > 9\n  }\n  return res.replace(/^0+/, '')\n}\t\n```\n\n",
  "body_draft": "",
  "body_html": "<!doctype html><pre data-lang=\"javascript\"><code>Number.MAX_VALUE // 1.7976931348623157e+308\nNumber.MAX_SAFE_INTEGER // 9007199254740991\nNumber.MIN_VALUE // 5e-324\nNumber.MIN_SAFE_INTEGER // -9007199254740991</code></pre><p data-lake-id=\"u5e042eac\"><span>如果想要对一个超大的整数(</span><code><span>&gt; Number.MAX_SAFE_INTEGER</span></code><span>)进行加法运算，但是又想输出一般形式，那么使用 + 是无法达到的，一旦数字超过 </span><code><span>Number.MAX_SAFE_INTEGER</span></code><span> 数字会被立即转换为科学计数法，并且数字精度相比以前将会有误差。</span></p><h2 id=\"Isqf4\"><span>利用算法实现大数相加</span></h2><h3 id=\"RxDUt\"><span>主要思路</span></h3><ul><li><span>首先用字符串的方式来保存大数，这样数字在数学表示上就不会发生变化</span></li><li><span>初始化 </span><code><span>res</span></code><span>，</span><code><span>temp</span></code><span> 来保存中间的计算结果，并将两个字符串转化为数组，以便进行每一位的加法运算</span></li><li><span>将两个数组的对应的位进行相加，两个数相加的结果可能大于 </span><code><span>10</span></code><span>，所以可能要仅为，对 </span><code><span>10</span></code><span> 进行取余操作，将结果保存在当前位</span></li><li><span>判断当前位是否大于 </span><code><span>9</span></code><span>，也就是是否会进位，若是则将 </span><code><span>temp</span></code><span> 赋值为 </span><code><span>true</span></code><span>，因为在加法运算中，</span><code><span>true</span></code><span> 会自动隐式转化为 </span><code><span>1</span></code><span>，以便于下一次相加</span></li><li><span>重复上述操作，直至计算结束</span></li></ul><h3 id=\"pVVrc\"><span>实现</span></h3><pre data-lang=\"javascript\"><code>function sumBigNumebr(a, b) {\n\tlet res = ''\n  let temp = 0\n  a = a.split('')\n  b = b.split('')\n  \n  while(a.length || b.length || temp) {\n  \ttemp += ~~a.pop() + ~~b.pop()\n    res = res + (temp % 10)\n    temp = temp &gt; 9\n  }\n  return res.replace(/^0+/, '')\n}\t</code></pre><p data-lake-id=\"u2cdc7c80\"><br /></p>",
  "body_lake": "<!doctype lake><meta name=\"doc-version\" content=\"1\" /><meta name=\"typography\" content=\"classic\" /><meta name=\"viewport\" content=\"adapt\" /><card type=\"inline\" name=\"codeblock\" value=\"data:%7B%22mode%22%3A%22javascript%22%2C%22code%22%3A%22Number.MAX_VALUE%20%2F%2F%201.7976931348623157e%2B308%5CnNumber.MAX_SAFE_INTEGER%20%2F%2F%209007199254740991%5CnNumber.MIN_VALUE%20%2F%2F%205e-324%5CnNumber.MIN_SAFE_INTEGER%20%2F%2F%20-9007199254740991%22%2C%22autoWrap%22%3Afalse%2C%22heightLimit%22%3Atrue%2C%22collapsed%22%3Afalse%2C%22name%22%3A%22%22%2C%22tabSize%22%3Anull%2C%22indentWithTab%22%3Afalse%2C%22lightLines%22%3A%5B%5D%2C%22foldLines%22%3A%5B%5D%2C%22theme%22%3A%22Night%20Owl%22%2C%22__spacing%22%3A%22both%22%2C%22id%22%3A%22rIcP6%22%2C%22margin%22%3A%7B%22top%22%3Atrue%2C%22bottom%22%3Atrue%7D%7D\"></card><p data-lake-id=\"u5e042eac\" id=\"u5e042eac\"><span data-lake-id=\"u632c3c27\" id=\"u632c3c27\">如果想要对一个超大的整数(</span><code data-lake-id=\"uca48a52e\" id=\"uca48a52e\"><span data-lake-id=\"uf271bd3f\" id=\"uf271bd3f\">&gt; Number.MAX_SAFE_INTEGER</span></code><span data-lake-id=\"u0dcd040b\" id=\"u0dcd040b\">)进行加法运算，但是又想输出一般形式，那么使用 + 是无法达到的，一旦数字超过 </span><code data-lake-id=\"uc4549f93\" id=\"uc4549f93\"><span data-lake-id=\"u3fc4c4c4\" id=\"u3fc4c4c4\">Number.MAX_SAFE_INTEGER</span></code><span data-lake-id=\"u330b32de\" id=\"u330b32de\"> 数字会被立即转换为科学计数法，并且数字精度相比以前将会有误差。</span></p><h2 data-lake-id=\"Isqf4\" id=\"Isqf4\"><span data-lake-id=\"u7dbd96f7\" id=\"u7dbd96f7\">利用算法实现大数相加</span></h2><h3 data-lake-id=\"RxDUt\" id=\"RxDUt\"><span data-lake-id=\"u9dbe116d\" id=\"u9dbe116d\">主要思路</span></h3><ul list=\"uccb33117\"><li fid=\"u753ca60b\" data-lake-id=\"ub467578d\" id=\"ub467578d\"><span data-lake-id=\"u49f5b8ae\" id=\"u49f5b8ae\">首先用字符串的方式来保存大数，这样数字在数学表示上就不会发生变化</span></li><li fid=\"u753ca60b\" data-lake-id=\"u15062f12\" id=\"u15062f12\"><span data-lake-id=\"ub2798e2f\" id=\"ub2798e2f\">初始化 </span><code data-lake-id=\"u452590a0\" id=\"u452590a0\"><span data-lake-id=\"u589600bb\" id=\"u589600bb\">res</span></code><span data-lake-id=\"u8a188acb\" id=\"u8a188acb\">，</span><code data-lake-id=\"u304cd17d\" id=\"u304cd17d\"><span data-lake-id=\"u34fe86a1\" id=\"u34fe86a1\">temp</span></code><span data-lake-id=\"u1ccbd5aa\" id=\"u1ccbd5aa\"> 来保存中间的计算结果，并将两个字符串转化为数组，以便进行每一位的加法运算</span></li><li fid=\"u753ca60b\" data-lake-id=\"ub7eb47b1\" id=\"ub7eb47b1\"><span data-lake-id=\"u422bed14\" id=\"u422bed14\">将两个数组的对应的位进行相加，两个数相加的结果可能大于 </span><code data-lake-id=\"uce9396c9\" id=\"uce9396c9\"><span data-lake-id=\"u79de0eea\" id=\"u79de0eea\">10</span></code><span data-lake-id=\"u80fed206\" id=\"u80fed206\">，所以可能要仅为，对 </span><code data-lake-id=\"uffc1b7a2\" id=\"uffc1b7a2\"><span data-lake-id=\"u3cabe048\" id=\"u3cabe048\">10</span></code><span data-lake-id=\"uc906b844\" id=\"uc906b844\"> 进行取余操作，将结果保存在当前位</span></li><li fid=\"u753ca60b\" data-lake-id=\"u49462a73\" id=\"u49462a73\"><span data-lake-id=\"ueee88092\" id=\"ueee88092\">判断当前位是否大于 </span><code data-lake-id=\"uc8ab67ff\" id=\"uc8ab67ff\"><span data-lake-id=\"u83ca79e2\" id=\"u83ca79e2\">9</span></code><span data-lake-id=\"ud81dc8e7\" id=\"ud81dc8e7\">，也就是是否会进位，若是则将 </span><code data-lake-id=\"u8381c804\" id=\"u8381c804\"><span data-lake-id=\"u49900dd2\" id=\"u49900dd2\">temp</span></code><span data-lake-id=\"u9ef0fa6f\" id=\"u9ef0fa6f\"> 赋值为 </span><code data-lake-id=\"ub1c63677\" id=\"ub1c63677\"><span data-lake-id=\"ub92b9c9f\" id=\"ub92b9c9f\">true</span></code><span data-lake-id=\"u9622a5ce\" id=\"u9622a5ce\">，因为在加法运算中，</span><code data-lake-id=\"uc87a54a8\" id=\"uc87a54a8\"><span data-lake-id=\"u3213eaff\" id=\"u3213eaff\">true</span></code><span data-lake-id=\"u13e4fd63\" id=\"u13e4fd63\"> 会自动隐式转化为 </span><code data-lake-id=\"ud76df607\" id=\"ud76df607\"><span data-lake-id=\"u219ac04d\" id=\"u219ac04d\">1</span></code><span data-lake-id=\"ub28b965e\" id=\"ub28b965e\">，以便于下一次相加</span></li><li fid=\"u753ca60b\" data-lake-id=\"ucf4b379c\" id=\"ucf4b379c\"><span data-lake-id=\"u1dcf1f52\" id=\"u1dcf1f52\">重复上述操作，直至计算结束</span></li></ul><h3 data-lake-id=\"pVVrc\" id=\"pVVrc\"><span data-lake-id=\"u0d293fea\" id=\"u0d293fea\">实现</span></h3><card type=\"inline\" name=\"codeblock\" value=\"data:%7B%22mode%22%3A%22javascript%22%2C%22code%22%3A%22function%20sumBigNumebr(a%2C%20b)%20%7B%5Cn%5Ctlet%20res%20%3D%20''%5Cn%20%20let%20temp%20%3D%200%5Cn%20%20a%20%3D%20a.split('')%5Cn%20%20b%20%3D%20b.split('')%5Cn%20%20%5Cn%20%20while(a.length%20%7C%7C%20b.length%20%7C%7C%20temp)%20%7B%5Cn%20%20%5Cttemp%20%2B%3D%20~~a.pop()%20%2B%20~~b.pop()%5Cn%20%20%20%20res%20%3D%20res%20%2B%20(temp%20%25%2010)%5Cn%20%20%20%20temp%20%3D%20temp%20%3E%209%5Cn%20%20%7D%5Cn%20%20return%20res.replace(%2F%5E0%2B%2F%2C%20'')%5Cn%7D%5Ct%22%2C%22autoWrap%22%3Afalse%2C%22heightLimit%22%3Atrue%2C%22collapsed%22%3Afalse%2C%22name%22%3A%22%22%2C%22tabSize%22%3Anull%2C%22indentWithTab%22%3Afalse%2C%22lightLines%22%3A%5B%5D%2C%22foldLines%22%3A%5B%5D%2C%22theme%22%3A%22One%20Dark%20Pro%22%2C%22__spacing%22%3A%22both%22%2C%22id%22%3A%22YAQSL%22%2C%22margin%22%3A%7B%22top%22%3Atrue%2C%22bottom%22%3Atrue%7D%7D\"></card><p data-lake-id=\"u2cdc7c80\" id=\"u2cdc7c80\"><br></p>",
  "body_draft_lake": "",
  "public": 0,
  "status": 1,
  "view_status": 0,
  "read_status": 1,
  "likes_count": 0,
  "comments_count": 0,
  "content_updated_at": "2022-04-04T11:35:19.000Z",
  "deleted_at": null,
  "created_at": "2022-04-04T11:35:19.000Z",
  "updated_at": "2022-05-10T15:16:48.000Z",
  "published_at": "2022-04-04T11:35:19.000Z",
  "first_published_at": "2022-04-04T11:35:19.388Z",
  "word_count": 358,
  "cover": null,
  "description": "Number.MAX_VALUE // 1.7976931348623157e+308 Number.MAX_SAFE_INTEGER // 9007199254740991 Number.MIN_VALUE // 5e-324 Number.MIN_SAFE_INTEGER // -9007...",
  "custom_description": null,
  "hits": 0,
  "_serializer": "v2.doc_detail"
}