{
  "id": 72212153,
  "slug": "hg8h4r",
  "title": "chunk 和 bundle 的区别",
  "book_id": 26225124,
  "book": {
    "id": 26225124,
    "type": "Book",
    "slug": "mxunh7",
    "name": "八股文 eight-part essay writing",
    "user_id": 732231,
    "description": "前端八股文",
    "creator_id": 732231,
    "public": 0,
    "items_count": 239,
    "likes_count": 0,
    "watches_count": 1,
    "content_updated_at": "2023-11-11T18:15:57.023Z",
    "updated_at": "2023-11-11T18:15:57.000Z",
    "created_at": "2022-04-04T11:31:45.000Z",
    "namespace": "wcywxq/mxunh7",
    "user": {
      "id": 732231,
      "type": "User",
      "login": "wcywxq",
      "name": "magic",
      "description": null,
      "avatar_url": "https://cdn.nlark.com/yuque/0/2020/png/732231/1606968271774-avatar/886ad88b-d2cc-4c9e-a674-f70eb51a679c.png",
      "books_count": 18,
      "public_books_count": 0,
      "followers_count": 0,
      "following_count": 0,
      "created_at": "2020-01-08T14:21:31.000Z",
      "updated_at": "2023-11-13T09:32:35.000Z",
      "_serializer": "v2.user"
    },
    "_serializer": "v2.book"
  },
  "user_id": 732231,
  "creator": {
    "id": 732231,
    "type": "User",
    "login": "wcywxq",
    "name": "magic",
    "description": null,
    "avatar_url": "https://cdn.nlark.com/yuque/0/2020/png/732231/1606968271774-avatar/886ad88b-d2cc-4c9e-a674-f70eb51a679c.png",
    "books_count": 18,
    "public_books_count": 0,
    "followers_count": 0,
    "following_count": 0,
    "created_at": "2020-01-08T14:21:31.000Z",
    "updated_at": "2023-11-13T09:32:35.000Z",
    "_serializer": "v2.user"
  },
  "format": "lake",
  "body": ":::info\n个人理解：<br />`chunk` 是过程，`bundle` 是结果，`chunk` 在构建完成时呈现为 `bundle`\n:::\n<a name=\"vMn5G\"></a>\n## chunk\n`chunk` 是 `webpack` 打包过程中 `modules` 的集合，是**打包过程中**的概念。<br />`webpack` 的打包是从一个入口模块开始，入口模块引用其他模块，其他模块引用其他模块，这样一直递归下去。<br />`webpack` 通过引用关系逐个打包模块，这些 `module` 就形成了一个 `chunk`，如果有多个入口模块，可能会产生多个打包路径，每条路径都会形成 `chunk`\n<a name=\"AxhEX\"></a>\n## bundle\n是最终输出的一个或多个打包好的文件\n<a name=\"rykJw\"></a>\n## chunk 和 bundle 的区别(关系)是什么\n大多数情况下，一个 `chunk` 会生产一个 `bundle`，但也有例外。如果加了 `sourceMap`，一个 `entry`，一个 `chunk` 对应两个 `bundle`\n<a name=\"Jvjn0\"></a>\n## split chunk\n做代码分割，可以通过配置增加\n",
  "body_draft": "",
  "body_html": "<!doctype html><blockquote class=\"lake-alert lake-alert-info\"><p data-lake-id=\"u760dd434\"><span>个人理解：</span></p><p data-lake-id=\"u5b9848d4\" style=\"text-indent: 2em;\"><code><span>chunk</span></code><span> 是过程，</span><code><span>bundle</span></code><span> 是结果，</span><code><span>chunk</span></code><span> 在构建完成时呈现为 </span><code><span>bundle</span></code></p></blockquote><h2 id=\"vMn5G\"><span>chunk</span></h2><p data-lake-id=\"ub35e05bd\" style=\"text-indent: 2em;\"><code><span>chunk</span></code><span> 是 </span><code><span>webpack</span></code><span> 打包过程中 </span><code><span>modules</span></code><span> 的集合，是</span><strong><span>打包过程中</span></strong><span>的概念。</span></p><p data-lake-id=\"udbe0ac70\" style=\"text-indent: 2em;\"><code><span>webpack</span></code><span> 的打包是从一个入口模块开始，入口模块引用其他模块，其他模块引用其他模块，这样一直递归下去。</span></p><p data-lake-id=\"ufa7de808\" style=\"text-indent: 2em;\"><code><span>webpack</span></code><span> 通过引用关系逐个打包模块，这些 </span><code><span>module</span></code><span> 就形成了一个 </span><code><span>chunk</span></code><span>，如果有多个入口模块，可能会产生多个打包路径，每条路径都会形成 </span><code><span>chunk</span></code></p><h2 id=\"AxhEX\"><span>bundle</span></h2><p data-lake-id=\"ufdcb8a3d\"><span>是最终输出的一个或多个打包好的文件</span></p><h2 id=\"rykJw\"><span>chunk 和 bundle 的区别(关系)是什么</span></h2><p data-lake-id=\"u204940e4\"><span>大多数情况下，一个 </span><code><span>chunk</span></code><span> 会生产一个 </span><code><span>bundle</span></code><span>，但也有例外。如果加了 </span><code><span>sourceMap</span></code><span>，一个 </span><code><span>entry</span></code><span>，一个 </span><code><span>chunk</span></code><span> 对应两个 </span><code><span>bundle</span></code></p><h2 id=\"Jvjn0\"><span>split chunk</span></h2><p data-lake-id=\"u6182d9d4\"><span>做代码分割，可以通过配置增加</span></p>",
  "body_lake": "<!doctype lake><meta name=\"doc-version\" content=\"1\" /><meta name=\"typography\" content=\"classic\" /><meta name=\"viewport\" content=\"adapt\" /><blockquote data-lake-id=\"u9ef4a5b8\" id=\"u9ef4a5b8\" class=\"lake-alert lake-alert-info\"><p data-lake-id=\"u760dd434\" id=\"u760dd434\"><span data-lake-id=\"uc949d7fe\" id=\"uc949d7fe\">个人理解：</span></p><p data-lake-id=\"u5b9848d4\" id=\"u5b9848d4\" style=\"text-indent: 2em\"><code data-lake-id=\"u3d574d46\" id=\"u3d574d46\"><span data-lake-id=\"u4c23fb2a\" id=\"u4c23fb2a\">chunk</span></code><span data-lake-id=\"ua2a3b87c\" id=\"ua2a3b87c\"> 是过程，</span><code data-lake-id=\"u419cdb21\" id=\"u419cdb21\"><span data-lake-id=\"u8ec24b46\" id=\"u8ec24b46\">bundle</span></code><span data-lake-id=\"u066a3bbd\" id=\"u066a3bbd\"> 是结果，</span><code data-lake-id=\"u524f54c3\" id=\"u524f54c3\"><span data-lake-id=\"u055214db\" id=\"u055214db\">chunk</span></code><span data-lake-id=\"ue0549bfe\" id=\"ue0549bfe\"> 在构建完成时呈现为 </span><code data-lake-id=\"u7a118b6c\" id=\"u7a118b6c\"><span data-lake-id=\"u9d50b7a7\" id=\"u9d50b7a7\">bundle</span></code></p></blockquote><h2 data-lake-id=\"vMn5G\" id=\"vMn5G\"><span data-lake-id=\"u34c68c9d\" id=\"u34c68c9d\">chunk</span></h2><p data-lake-id=\"ub35e05bd\" id=\"ub35e05bd\" style=\"text-indent: 2em\"><code data-lake-id=\"uc05da9f3\" id=\"uc05da9f3\"><span data-lake-id=\"u46343901\" id=\"u46343901\">chunk</span></code><span data-lake-id=\"u4b765ece\" id=\"u4b765ece\"> 是 </span><code data-lake-id=\"u349d2031\" id=\"u349d2031\"><span data-lake-id=\"u3e6ee64c\" id=\"u3e6ee64c\">webpack</span></code><span data-lake-id=\"ub5983203\" id=\"ub5983203\"> 打包过程中 </span><code data-lake-id=\"ubee9aec2\" id=\"ubee9aec2\"><span data-lake-id=\"u40c691ec\" id=\"u40c691ec\">modules</span></code><span data-lake-id=\"u290db011\" id=\"u290db011\"> 的集合，是</span><strong><span data-lake-id=\"u2bd3f6e9\" id=\"u2bd3f6e9\">打包过程中</span></strong><span data-lake-id=\"ufaf3d12a\" id=\"ufaf3d12a\">的概念。</span></p><p data-lake-id=\"udbe0ac70\" id=\"udbe0ac70\" style=\"text-indent: 2em\"><code data-lake-id=\"u413f0d07\" id=\"u413f0d07\"><span data-lake-id=\"u2e5bd038\" id=\"u2e5bd038\">webpack</span></code><span data-lake-id=\"u9a178442\" id=\"u9a178442\"> 的打包是从一个入口模块开始，入口模块引用其他模块，其他模块引用其他模块，这样一直递归下去。</span></p><p data-lake-id=\"ufa7de808\" id=\"ufa7de808\" style=\"text-indent: 2em\"><code data-lake-id=\"u52665deb\" id=\"u52665deb\"><span data-lake-id=\"u73c713f2\" id=\"u73c713f2\">webpack</span></code><span data-lake-id=\"u19476954\" id=\"u19476954\"> 通过引用关系逐个打包模块，这些 </span><code data-lake-id=\"u23d5b0ae\" id=\"u23d5b0ae\"><span data-lake-id=\"ueabd66fa\" id=\"ueabd66fa\">module</span></code><span data-lake-id=\"u5ba6ff3c\" id=\"u5ba6ff3c\"> 就形成了一个 </span><code data-lake-id=\"u0f13278a\" id=\"u0f13278a\"><span data-lake-id=\"uf1b86f85\" id=\"uf1b86f85\">chunk</span></code><span data-lake-id=\"ue0aab478\" id=\"ue0aab478\">，如果有多个入口模块，可能会产生多个打包路径，每条路径都会形成 </span><code data-lake-id=\"u6d4f42ad\" id=\"u6d4f42ad\"><span data-lake-id=\"u1e94a135\" id=\"u1e94a135\">chunk</span></code></p><h2 data-lake-id=\"AxhEX\" id=\"AxhEX\"><span data-lake-id=\"u03877a17\" id=\"u03877a17\">bundle</span></h2><p data-lake-id=\"ufdcb8a3d\" id=\"ufdcb8a3d\"><span data-lake-id=\"u67c40ecf\" id=\"u67c40ecf\">是最终输出的一个或多个打包好的文件</span></p><h2 data-lake-id=\"rykJw\" id=\"rykJw\"><span data-lake-id=\"u1c629948\" id=\"u1c629948\">chunk 和 bundle 的区别(关系)是什么</span></h2><p data-lake-id=\"u204940e4\" id=\"u204940e4\"><span data-lake-id=\"u25c5d317\" id=\"u25c5d317\">大多数情况下，一个 </span><code data-lake-id=\"u47877e47\" id=\"u47877e47\"><span data-lake-id=\"u9aef86c2\" id=\"u9aef86c2\">chunk</span></code><span data-lake-id=\"u6364c7aa\" id=\"u6364c7aa\"> 会生产一个 </span><code data-lake-id=\"u994e580e\" id=\"u994e580e\"><span data-lake-id=\"u898ba573\" id=\"u898ba573\">bundle</span></code><span data-lake-id=\"uf0297f15\" id=\"uf0297f15\">，但也有例外。如果加了 </span><code data-lake-id=\"ua9be6e2a\" id=\"ua9be6e2a\"><span data-lake-id=\"uca88d7e7\" id=\"uca88d7e7\">sourceMap</span></code><span data-lake-id=\"u2ad7f4ab\" id=\"u2ad7f4ab\">，一个 </span><code data-lake-id=\"u5941b888\" id=\"u5941b888\"><span data-lake-id=\"u5c9139a7\" id=\"u5c9139a7\">entry</span></code><span data-lake-id=\"u40f65240\" id=\"u40f65240\">，一个 </span><code data-lake-id=\"u8985e2b3\" id=\"u8985e2b3\"><span data-lake-id=\"uabe82edf\" id=\"uabe82edf\">chunk</span></code><span data-lake-id=\"u361cb4b1\" id=\"u361cb4b1\"> 对应两个 </span><code data-lake-id=\"ua550ff57\" id=\"ua550ff57\"><span data-lake-id=\"u3672a656\" id=\"u3672a656\">bundle</span></code></p><h2 data-lake-id=\"Jvjn0\" id=\"Jvjn0\"><span data-lake-id=\"u15bc0c78\" id=\"u15bc0c78\">split chunk</span></h2><p data-lake-id=\"u6182d9d4\" id=\"u6182d9d4\"><span data-lake-id=\"u83571c9c\" id=\"u83571c9c\">做代码分割，可以通过配置增加</span></p>",
  "body_draft_lake": "",
  "public": 0,
  "status": 1,
  "view_status": 0,
  "read_status": 1,
  "likes_count": 0,
  "comments_count": 0,
  "content_updated_at": "2022-04-04T11:33:20.000Z",
  "deleted_at": null,
  "created_at": "2022-04-04T11:33:20.000Z",
  "updated_at": "2022-05-10T15:12:38.000Z",
  "published_at": "2022-04-04T11:33:20.000Z",
  "first_published_at": "2022-04-04T11:33:19.826Z",
  "word_count": 240,
  "cover": null,
  "description": "个人理解：chunk 是过程，bundle 是结果，chunk 在构建完成时呈现为 bundlechunkchunk 是 webpack 打包过程中 modules 的集合，是打包过程中的概念。webpack 的打包是从一个入口模块开始，入口模块引用其他模块，其他模块引用其他模块，这样一直递归...",
  "custom_description": null,
  "hits": 0,
  "_serializer": "v2.doc_detail"
}